awslabs/__init__.py
awslabs/finch_mcp_server/__init__.py
awslabs/finch_mcp_server/consts.py
awslabs/finch_mcp_server/models.py
awslabs/finch_mcp_server/server.py
awslabs/finch_mcp_server/utils/__init__.py
awslabs/finch_mcp_server/utils/build.py
awslabs/finch_mcp_server/utils/common.py
awslabs/finch_mcp_server/utils/ecr.py
awslabs/finch_mcp_server/utils/push.py
awslabs/finch_mcp_server/utils/vm.py
awslabs_finch_mcp_server-0.1.13.dist-info/METADATA
awslabs_finch_mcp_server-0.1.13.dist-info/WHEEL
awslabs_finch_mcp_server-0.1.13.dist-info/entry_points.txt
awslabs_finch_mcp_server-0.1.13.dist-info/licenses/LICENSE
awslabs_finch_mcp_server-0.1.13.dist-info/licenses/NOTICE
awslabs_finch_mcp_server-0.1.13.dist-info/RECORD
